superclient/__init__.py
superclient/__main__.py
superclient/install_pth.py
superclient/superclient-init.pth
superclient/agent/__init__.py
superclient/agent/interceptor.py
superclient/agent/metadata.py
superclient/agent/tracker.py
superclient/core/manager.py
superclient/core/reporter.py
superclient/model/messages.py
superclient/util/config.py
superclient/util/logger.py
superclient/util/metrics.py
superclient/util/network.py
superstream_clients_beta-1.0.3.dist-info/licenses/LICENSE
superstream_clients_beta-1.0.3.dist-info/METADATA
superstream_clients_beta-1.0.3.dist-info/WHEEL
superstream_clients_beta-1.0.3.dist-info/top_level.txt
superstream_clients_beta-1.0.3.dist-info/RECORD
